mo_vector/__init__.py
mo_vector/client/__init__.py
mo_vector/client/query_result.py
mo_vector/client/utils.py
mo_vector/client/vector_client.py
mo_vector/constants.py
mo_vector/sqlalchemy/__init__.py
mo_vector/sqlalchemy/adaptor.py
mo_vector/sqlalchemy/vector_type.py
mo_vector/utils.py
mo_vector-0.1.13.dist-info/LICENSE
mo_vector-0.1.13.dist-info/METADATA
mo_vector-0.1.13.dist-info/WHEEL
mo_vector-0.1.13.dist-info/RECORD
